earlyexit/__init__.py
earlyexit/cli.py
earlyexit/commands.py
earlyexit/inference.py
earlyexit/telemetry.py
earlyexit/telemetry_cli.py
earlyexit-0.0.3.dist-info/licenses/LICENSE
earlyexit-0.0.3.dist-info/METADATA
earlyexit-0.0.3.dist-info/WHEEL
earlyexit-0.0.3.dist-info/entry_points.txt
earlyexit-0.0.3.dist-info/top_level.txt
earlyexit-0.0.3.dist-info/RECORD
