Metadata-Version: 2.4
Name: earlyexit
Version: 0.0.3
Summary: Early exit pattern matching for command output with fast error detection
Author-email: Robert Lee <robert.lee@databricks.com>
License: MIT
Project-URL: Homepage, https://github.com/rsleedbx/earlyexit
Project-URL: Repository, https://github.com/rsleedbx/earlyexit
Project-URL: Bug Tracker, https://github.com/rsleedbx/earlyexit/issues
Keywords: cli,grep,pattern-matching,early-exit,fail-fast,monitoring
Classifier: Development Status :: 4 - Beta
Classifier: Intended Audience :: Developers
Classifier: Intended Audience :: System Administrators
Classifier: License :: OSI Approved :: MIT License
Classifier: Programming Language :: Python :: 3
Classifier: Programming Language :: Python :: 3.7
Classifier: Programming Language :: Python :: 3.8
Classifier: Programming Language :: Python :: 3.9
Classifier: Programming Language :: Python :: 3.10
Classifier: Programming Language :: Python :: 3.11
Classifier: Topic :: Software Development :: Testing
Classifier: Topic :: System :: Monitoring
Classifier: Topic :: Utilities
Requires-Python: >=3.7
License-File: LICENSE
Requires-Dist: psutil>=5.8.0
Requires-Dist: tenacity>=8.0.0
Provides-Extra: perl
Requires-Dist: regex; extra == "perl"
Dynamic: license-file
